Grank-1.0.4.dist-info/DESCRIPTION.rst
Grank-1.0.4.dist-info/METADATA
Grank-1.0.4.dist-info/RECORD
Grank-1.0.4.dist-info/WHEEL
Grank-1.0.4.dist-info/entry_points.txt
Grank-1.0.4.dist-info/metadata.json
Grank-1.0.4.dist-info/top_level.txt
grank/__init__.py
grank/core.py
grank/libs/__init__.py
grank/libs/helpers.py
grank/libs/query.py
grank/script/__init__.py
grank/script/activity.py
grank/script/crawler.py
grank/script/social.py
tests/__init__.py
tests/test_basic.py
tests/test_helpers.py
