Metadata-Version: 2.0
Name: Grank
Version: 1.0.4
Summary: A Github Project Rank Command Line Tool
Home-page: https://github.com/LCTT/Grank
Author: LCTT
Author-email: xiqingongzi@gmail.com
License: GPLv3
Project-URL: Bug Tracker, https://github.com/LCTT/Grank/issues
Project-URL: Documentation, https://github.com/LCTT/Grank
Project-URL: Source Code, https://github.com/LCTT/Grank
Platform: UNKNOWN
Classifier: Programming Language :: Python :: 3
Requires-Python: >=3.4
Requires-Dist: click
Requires-Dist: requests
Requires-Dist: pandas
Requires-Dist: numpy
Requires-Dist: matplotlib
